inspectr/__init__.py
inspectr/__main__.py
inspectr/authenticity.py
inspectr/bare_ratio.py
inspectr/compare_funcs.py
inspectr/complexity.py
inspectr/count_exceptions.py
inspectr/duplicates.py
inspectr/size_counts.py
inspectr/with_open.py
inspectr-0.1.2.dist-info/licenses/LICENSE
inspectr-0.1.2.dist-info/METADATA
inspectr-0.1.2.dist-info/WHEEL
inspectr-0.1.2.dist-info/entry_points.txt
inspectr-0.1.2.dist-info/top_level.txt
inspectr-0.1.2.dist-info/RECORD
