Metadata-Version: 2.4
Name: inspectr
Version: 0.1.2
Summary: A collection of python tools to inspect code quality. 
Maintainer-email: Alex Mueller <amueller474@gmail.com>
License-Expression: Apache-2.0
Project-URL: Homepage, https://github.com/ajcm474/inspectr
Project-URL: Issues, https://github.com/ajcm474/inspectr/issues
Classifier: Development Status :: 3 - Alpha
Classifier: Intended Audience :: Developers
Classifier: Programming Language :: Python
Classifier: Programming Language :: Python :: 3
Classifier: Programming Language :: Python :: 3 :: Only
Classifier: Topic :: Software Development
License-File: LICENSE
Requires-Dist: colorama
Provides-Extra: test
Requires-Dist: pytest; extra == "test"
Dynamic: license-file
